{"cameraMode":{"drawMode":0,"name":"Shaded","section":"Shading Mode"},"sceneLighting":true,"audioPlay":false,"sceneViewState":{"m_AlwaysRefresh":false,"showFog":true,"showSkybox":true,"showFlares":true,"showImageEffects":true,"showParticleSystems":true,"showVisualEffectGraphs":true,"m_FxEnabled":true},"in2DMode":false,"pivot":{"x":2.372915267944336,"y":1.9901251792907715,"z":-3.970127820968628},"rotation":{"x":0.07504390180110932,"y":-0.33663392066955569,"z":0.026937413960695268,"w":0.9383677244186401},"size":1.360663890838623,"orthographic":false}